ginput/__init__.py
ginput/common_utils/__init__.py
ginput/common_utils/ggg_logging.py
ginput/common_utils/ioutils.py
ginput/common_utils/mod_constants.py
ginput/common_utils/mod_utils.py
ginput/common_utils/readers.py
ginput/common_utils/run_utils.py
ginput/common_utils/sat_utils.py
ginput/common_utils/versioning.py
ginput/common_utils/writers.py
ginput/data/.gitignore
ginput/data/GEOS_FPIT_lat_vs_theta_2018_500-700hPa.nc
ginput/data/ML_monthly_obs_ch4.txt
ginput/data/ML_monthly_obs_co.txt
ginput/data/ML_monthly_obs_co2.txt
ginput/data/ML_monthly_obs_n2o.txt
ginput/data/SMO_monthly_obs_ch4.txt
ginput/data/SMO_monthly_obs_co.txt
ginput/data/SMO_monthly_obs_co2.txt
ginput/data/SMO_monthly_obs_n2o.txt
ginput/data/ace_fn2o_lut.nc
ginput/data/ch4_hf_slopes.nc
ginput/data/clams_age_clim_scaled.nc
ginput/data/isotopologs.dat
ginput/data/meso_co_lut.nc
ginput/data/n2o_ch4_acefts.nc
ginput/data/summer_35N.vmr
ginput/data/washenfelder03_table_s3.txt
ginput/data/age_spectra/age.midlat.txt
ginput/data/age_spectra/age.tropics.txt
ginput/data/age_spectra/age.vortex.txt
ginput/data/age_spectra/agespec.midlat.txt
ginput/data/age_spectra/agespec.tropics.txt
ginput/data/age_spectra/agespec.vortex.txt
ginput/data/age_spectra/time.txt
ginput/data/fo2_data/.gitignore
ginput/data/noaa_data/20250507/ch4_mko_surface-flask_1_ccgg_event.txt
ginput/data/noaa_data/20250507/ch4_mko_surface-pfp_1_ccgg_event.txt
ginput/data/noaa_data/20250507/ch4_mlo_surface-flask_1_ccgg_month.txt
ginput/data/noaa_data/20250507/ch4_mlo_surface-insitu_1_ccgg_MonthlyData.txt
ginput/data/noaa_data/20250507/ch4_smo_surface-flask_1_ccgg_month.txt
ginput/data/noaa_data/20250507/co2_mko_surface-flask_1_ccgg_event.txt
ginput/data/noaa_data/20250507/co2_mko_surface-pfp_1_ccgg_event.txt
ginput/data/noaa_data/20250507/co2_mlo_surface-flask_1_ccgg_month.txt
ginput/data/noaa_data/20250507/co2_mlo_surface-insitu_1_ccgg_MonthlyData.txt
ginput/data/noaa_data/20250507/co2_smo_surface-flask_1_ccgg_month.txt
ginput-1.5.1.dist-info/licenses/LICENSE.txt
ginput-1.5.1.dist-info/METADATA
ginput-1.5.1.dist-info/WHEEL
ginput-1.5.1.dist-info/top_level.txt
ginput-1.5.1.dist-info/RECORD
