Metadata-Version: 2.4
Name: ginput
Version: 1.5.1
Summary: Python code that creates the .mod and .vmr files used in GGG
Home-page: 
Author: Joshua Laughner, Sebastien Roche, Matthaeus Kiel
Author-email: jllacct119@gmail.com
License-File: LICENSE.txt
Requires-Dist: astropy>=3.1.2
Requires-Dist: cfunits>=3.3.2
Requires-Dist: ephem>=3.7.6.0
Requires-Dist: h5py>=2.9.0
Requires-Dist: jplephem>=2.9
Requires-Dist: matplotlib>=3.0.3
Requires-Dist: netCDF4>=1.4.2
Requires-Dist: numpy>=1.23.0
Requires-Dist: pandas>=1.0.0
Requires-Dist: pydap>=3.2.2
Requires-Dist: python-dateutil>=2.8.2
Requires-Dist: requests>=2.14.2
Requires-Dist: scipy>=1.5.4
Requires-Dist: sgp4>=1.4
Requires-Dist: skyfield>=1.10
Requires-Dist: xarray>=0.12.1
Dynamic: author
Dynamic: author-email
Dynamic: description
Dynamic: description-content-type
Dynamic: license-file
Dynamic: requires-dist
Dynamic: summary
